mui/__init__.py
mui/compat.py
mui/py.typed
mui/v5/__init__.py
mui/v5/grid/__init__.py
mui/v5/grid/base.py
mui/v5/grid/filter/__init__.py
mui/v5/grid/filter/item.py
mui/v5/grid/filter/model.py
mui/v5/grid/link/__init__.py
mui/v5/grid/link/operator.py
mui/v5/grid/pagination/__init__.py
mui/v5/grid/pagination/model.py
mui/v5/grid/request.py
mui/v5/grid/sort/__init__.py
mui/v5/grid/sort/direction.py
mui/v5/grid/sort/item.py
mui/v5/grid/sort/model.py
mui/v5/integrations/__init__.py
mui/v5/integrations/flask/__init__.py
mui/v5/integrations/flask/filter/__init__.py
mui/v5/integrations/flask/filter/model.py
mui/v5/integrations/flask/pagination/__init__.py
mui/v5/integrations/flask/pagination/model.py
mui/v5/integrations/flask/request.py
mui/v5/integrations/flask/sort/__init__.py
mui/v5/integrations/flask/sort/model.py
mui/v5/integrations/flask/timezone/__init__.py
mui/v5/integrations/flask/timezone/model.py
mui/v5/integrations/sqlalchemy/__init__.py
mui/v5/integrations/sqlalchemy/apply_models.py
mui/v5/integrations/sqlalchemy/filter/__init__.py
mui/v5/integrations/sqlalchemy/filter/applicators/__init__.py
mui/v5/integrations/sqlalchemy/filter/applicators/after.py
mui/v5/integrations/sqlalchemy/filter/applicators/basic.py
mui/v5/integrations/sqlalchemy/filter/applicators/before.py
mui/v5/integrations/sqlalchemy/filter/applicators/contains.py
mui/v5/integrations/sqlalchemy/filter/applicators/endswith.py
mui/v5/integrations/sqlalchemy/filter/applicators/is_.py
mui/v5/integrations/sqlalchemy/filter/applicators/is_any_of.py
mui/v5/integrations/sqlalchemy/filter/applicators/is_empty.py
mui/v5/integrations/sqlalchemy/filter/applicators/is_not_empty.py
mui/v5/integrations/sqlalchemy/filter/applicators/not_.py
mui/v5/integrations/sqlalchemy/filter/applicators/on_or_after.py
mui/v5/integrations/sqlalchemy/filter/applicators/on_or_before.py
mui/v5/integrations/sqlalchemy/filter/applicators/startswith.py
mui/v5/integrations/sqlalchemy/filter/apply_items.py
mui_data_grid-0.15.0.dist-info/LICENSE
mui_data_grid-0.15.0.dist-info/METADATA
mui_data_grid-0.15.0.dist-info/WHEEL
mui_data_grid-0.15.0.dist-info/RECORD
