Metadata-Version: 2.3
Name: mui-data-grid
Version: 0.15.0
Summary: Unofficial backend utilities for using Material-UI's X-Data-Grid component
License: MIT
Author: Kevin Kirsche
Author-email: kev.kirsche@gmail.com
Requires-Python: >=3.9,<4
Classifier: License :: OSI Approved :: MIT License
Classifier: Programming Language :: Python :: 3
Classifier: Programming Language :: Python :: 3.9
Classifier: Programming Language :: Python :: 3.10
Classifier: Programming Language :: Python :: 3.11
Classifier: Programming Language :: Python :: 3.12
Classifier: Programming Language :: Python :: 3.13
Requires-Dist: pydantic (>=2.3.0,<3)
Requires-Dist: typing-extensions (>=4.7.1,<5)
Requires-Dist: tzdata (>=2024.2) ; sys_platform == "win32"
Project-URL: Repository, https://github.com/kkirsche/mui-data-grid
